brillouin_imaging/__init__.py
brillouin_imaging/_reader.py
brillouin_imaging/_sample_data.py
brillouin_imaging/_version.py
brillouin_imaging/napari.yaml
brillouin_imaging/test.py
brillouin_imaging/_tests/__init__.py
brillouin_imaging/_tests/test_reader.py
brillouin_imaging/_tests/test_sample_data.py
brillouin_imaging-0.1.0.dist-info/licenses/LICENSE
brillouin_imaging-0.1.0.dist-info/METADATA
brillouin_imaging-0.1.0.dist-info/WHEEL
brillouin_imaging-0.1.0.dist-info/entry_points.txt
brillouin_imaging-0.1.0.dist-info/top_level.txt
brillouin_imaging-0.1.0.dist-info/RECORD
